solr_dsl/__init__.py
solr_dsl/add.py
solr_dsl/cursor.py
solr_dsl/delete.py
solr_dsl/query.py
solr_dsl/search.py
solr_dsl/solr.py
solr_dsl-0.0.15.dist-info/LICENSE
solr_dsl-0.0.15.dist-info/METADATA
solr_dsl-0.0.15.dist-info/WHEEL
solr_dsl-0.0.15.dist-info/top_level.txt
solr_dsl-0.0.15.dist-info/RECORD
