Metadata-Version: 2.1
Name: solr-dsl
Version: 0.0.15
Summary: Python client for Solr
Home-page: https://github.com/it-com-engineering/solr-dsl
Author: Elliot Penson
Author-email: elliotpenson@gmail.com
License: UNKNOWN
Platform: UNKNOWN
Classifier: Programming Language :: Python :: 3
Classifier: License :: OSI Approved :: MIT License
Classifier: Operating System :: OS Independent
